duq/__init__.py
duq/dimension.py
duq/helpers.py
duq/quantity.py
duq/unit.py
duq/data/__init__.py
duq/data/dimensions_units.py
duq/data/metric_prefixes.py
duq/data/physical_constants.py
duq/data/unicode_chars.py
duq-0.0.1.dist-info/LICENSE
duq-0.0.1.dist-info/METADATA
duq-0.0.1.dist-info/WHEEL
duq-0.0.1.dist-info/top_level.txt
duq-0.0.1.dist-info/RECORD
